meowfacts/__init__.py
meowfacts/cli.py
meowfacts-1.1.0.dist-info/LICENSE
meowfacts-1.1.0.dist-info/METADATA
meowfacts-1.1.0.dist-info/WHEEL
meowfacts-1.1.0.dist-info/entry_points.txt
meowfacts-1.1.0.dist-info/top_level.txt
meowfacts-1.1.0.dist-info/RECORD
